{
    "assignee": null,
    "assignees": [],
    "author_association": "MEMBER",
    "body": "类似 #11 \r\n\r\n`gettingStarted`->`采煤出发`",
    "closed_at": "2018-12-02T07:54:30Z",
    "comment_data": [],
    "comments": 0,
    "comments_url": "https://api.github.com/repos/program-in-chinese/vscode_english_chinese_dictionary/issues/14/comments",
    "created_at": "2018-12-01T22:05:06Z",
    "event_data": [
        {
            "actor": {
                "avatar_url": "https://avatars1.githubusercontent.com/u/392497?v=4",
                "events_url": "https://api.github.com/users/nobodxbodon/events{/privacy}",
                "followers_url": "https://api.github.com/users/nobodxbodon/followers",
                "following_url": "https://api.github.com/users/nobodxbodon/following{/other_user}",
                "gists_url": "https://api.github.com/users/nobodxbodon/gists{/gist_id}",
                "gravatar_id": "",
                "html_url": "https://github.com/nobodxbodon",
                "id": 392497,
                "login": "nobodxbodon",
                "node_id": "MDQ6VXNlcjM5MjQ5Nw==",
                "organizations_url": "https://api.github.com/users/nobodxbodon/orgs",
                "received_events_url": "https://api.github.com/users/nobodxbodon/received_events",
                "repos_url": "https://api.github.com/users/nobodxbodon/repos",
                "site_admin": false,
                "starred_url": "https://api.github.com/users/nobodxbodon/starred{/owner}{/repo}",
                "subscriptions_url": "https://api.github.com/users/nobodxbodon/subscriptions",
                "type": "User",
                "url": "https://api.github.com/users/nobodxbodon"
            },
            "commit_id": "167306fb35f5a9f16277c32e4ec9cf0093f7828b",
            "commit_url": "https://api.github.com/repos/program-in-chinese/vscode_english_chinese_dictionary/commits/167306fb35f5a9f16277c32e4ec9cf0093f7828b",
            "created_at": "2018-12-02T03:52:28Z",
            "event": "referenced",
            "id": 1999795296,
            "node_id": "MDE1OlJlZmVyZW5jZWRFdmVudDE5OTk3OTUyOTY=",
            "url": "https://api.github.com/repos/program-in-chinese/vscode_english_chinese_dictionary/issues/events/1999795296"
        },
        {
            "actor": {
                "avatar_url": "https://avatars1.githubusercontent.com/u/392497?v=4",
                "events_url": "https://api.github.com/users/nobodxbodon/events{/privacy}",
                "followers_url": "https://api.github.com/users/nobodxbodon/followers",
                "following_url": "https://api.github.com/users/nobodxbodon/following{/other_user}",
                "gists_url": "https://api.github.com/users/nobodxbodon/gists{/gist_id}",
                "gravatar_id": "",
                "html_url": "https://github.com/nobodxbodon",
                "id": 392497,
                "login": "nobodxbodon",
                "node_id": "MDQ6VXNlcjM5MjQ5Nw==",
                "organizations_url": "https://api.github.com/users/nobodxbodon/orgs",
                "received_events_url": "https://api.github.com/users/nobodxbodon/received_events",
                "repos_url": "https://api.github.com/users/nobodxbodon/repos",
                "site_admin": false,
                "starred_url": "https://api.github.com/users/nobodxbodon/starred{/owner}{/repo}",
                "subscriptions_url": "https://api.github.com/users/nobodxbodon/subscriptions",
                "type": "User",
                "url": "https://api.github.com/users/nobodxbodon"
            },
            "commit_id": null,
            "commit_url": null,
            "created_at": "2018-12-02T07:54:30Z",
            "event": "closed",
            "id": 1999850812,
            "node_id": "MDExOkNsb3NlZEV2ZW50MTk5OTg1MDgxMg==",
            "url": "https://api.github.com/repos/program-in-chinese/vscode_english_chinese_dictionary/issues/events/1999850812"
        }
    ],
    "events_url": "https://api.github.com/repos/program-in-chinese/vscode_english_chinese_dictionary/issues/14/events",
    "html_url": "https://github.com/program-in-chinese/vscode_english_chinese_dictionary/issues/14",
    "id": 386502353,
    "labels": [],
    "labels_url": "https://api.github.com/repos/program-in-chinese/vscode_english_chinese_dictionary/issues/14/labels{/name}",
    "locked": false,
    "milestone": null,
    "node_id": "MDU6SXNzdWUzODY1MDIzNTM=",
    "number": 14,
    "repository_url": "https://api.github.com/repos/program-in-chinese/vscode_english_chinese_dictionary",
    "state": "closed",
    "title": "命名中, 如有现在分词, 采用原型释义",
    "updated_at": "2018-12-02T07:54:30Z",
    "url": "https://api.github.com/repos/program-in-chinese/vscode_english_chinese_dictionary/issues/14",
    "user": {
        "avatar_url": "https://avatars1.githubusercontent.com/u/392497?v=4",
        "events_url": "https://api.github.com/users/nobodxbodon/events{/privacy}",
        "followers_url": "https://api.github.com/users/nobodxbodon/followers",
        "following_url": "https://api.github.com/users/nobodxbodon/following{/other_user}",
        "gists_url": "https://api.github.com/users/nobodxbodon/gists{/gist_id}",
        "gravatar_id": "",
        "html_url": "https://github.com/nobodxbodon",
        "id": 392497,
        "login": "nobodxbodon",
        "node_id": "MDQ6VXNlcjM5MjQ5Nw==",
        "organizations_url": "https://api.github.com/users/nobodxbodon/orgs",
        "received_events_url": "https://api.github.com/users/nobodxbodon/received_events",
        "repos_url": "https://api.github.com/users/nobodxbodon/repos",
        "site_admin": false,
        "starred_url": "https://api.github.com/users/nobodxbodon/starred{/owner}{/repo}",
        "subscriptions_url": "https://api.github.com/users/nobodxbodon/subscriptions",
        "type": "User",
        "url": "https://api.github.com/users/nobodxbodon"
    }
}