{
    "assignee": null,
    "assignees": [],
    "author_association": "MEMBER",
    "body": "现在还是全中文. [mdn Internationalization文档](https://developer.mozilla.org/en-US/Add-ons/WebExtensions/Internationalization)",
    "closed_at": "2017-09-03T23:11:11Z",
    "comment_data": [
        {
            "author_association": "MEMBER",
            "body": "根据https://discourse.mozilla.org/t/we-i18n-could-use-a-getaddonlanguage-function/14982, 侧栏的多语言支持有限. 决定暂时用全英文界面, 由于50%的用户用的是英文版火狐.",
            "created_at": "2017-09-03T05:40:15Z",
            "html_url": "https://github.com/program-in-chinese/HistoryInThreads_WebExtension/issues/3#issuecomment-326785670",
            "id": 326785670,
            "issue_url": "https://api.github.com/repos/program-in-chinese/HistoryInThreads_WebExtension/issues/3",
            "node_id": "MDEyOklzc3VlQ29tbWVudDMyNjc4NTY3MA==",
            "updated_at": "2017-09-03T05:40:15Z",
            "url": "https://api.github.com/repos/program-in-chinese/HistoryInThreads_WebExtension/issues/comments/326785670",
            "user": {
                "avatar_url": "https://avatars1.githubusercontent.com/u/392497?v=4",
                "events_url": "https://api.github.com/users/nobodxbodon/events{/privacy}",
                "followers_url": "https://api.github.com/users/nobodxbodon/followers",
                "following_url": "https://api.github.com/users/nobodxbodon/following{/other_user}",
                "gists_url": "https://api.github.com/users/nobodxbodon/gists{/gist_id}",
                "gravatar_id": "",
                "html_url": "https://github.com/nobodxbodon",
                "id": 392497,
                "login": "nobodxbodon",
                "node_id": "MDQ6VXNlcjM5MjQ5Nw==",
                "organizations_url": "https://api.github.com/users/nobodxbodon/orgs",
                "received_events_url": "https://api.github.com/users/nobodxbodon/received_events",
                "repos_url": "https://api.github.com/users/nobodxbodon/repos",
                "site_admin": false,
                "starred_url": "https://api.github.com/users/nobodxbodon/starred{/owner}{/repo}",
                "subscriptions_url": "https://api.github.com/users/nobodxbodon/subscriptions",
                "type": "User",
                "url": "https://api.github.com/users/nobodxbodon"
            }
        },
        {
            "author_association": "NONE",
            "body": "对于html元素，以ID或其他方式获取元素然后`i18n.getMessage`赋值是目前的主流方法，Chrome扩展也如此。",
            "created_at": "2017-09-03T10:17:43Z",
            "html_url": "https://github.com/program-in-chinese/HistoryInThreads_WebExtension/issues/3#issuecomment-326796160",
            "id": 326796160,
            "issue_url": "https://api.github.com/repos/program-in-chinese/HistoryInThreads_WebExtension/issues/3",
            "node_id": "MDEyOklzc3VlQ29tbWVudDMyNjc5NjE2MA==",
            "updated_at": "2017-09-03T10:17:43Z",
            "url": "https://api.github.com/repos/program-in-chinese/HistoryInThreads_WebExtension/issues/comments/326796160",
            "user": {
                "avatar_url": "https://avatars0.githubusercontent.com/u/1769875?v=4",
                "events_url": "https://api.github.com/users/yfdyh000/events{/privacy}",
                "followers_url": "https://api.github.com/users/yfdyh000/followers",
                "following_url": "https://api.github.com/users/yfdyh000/following{/other_user}",
                "gists_url": "https://api.github.com/users/yfdyh000/gists{/gist_id}",
                "gravatar_id": "",
                "html_url": "https://github.com/yfdyh000",
                "id": 1769875,
                "login": "yfdyh000",
                "node_id": "MDQ6VXNlcjE3Njk4NzU=",
                "organizations_url": "https://api.github.com/users/yfdyh000/orgs",
                "received_events_url": "https://api.github.com/users/yfdyh000/received_events",
                "repos_url": "https://api.github.com/users/yfdyh000/repos",
                "site_admin": false,
                "starred_url": "https://api.github.com/users/yfdyh000/starred{/owner}{/repo}",
                "subscriptions_url": "https://api.github.com/users/yfdyh000/subscriptions",
                "type": "User",
                "url": "https://api.github.com/users/yfdyh000"
            }
        },
        {
            "author_association": "MEMBER",
            "body": "多谢! 其实之前试了在sidebar/main.js开头加这个:\r\n```\r\n  $(\"#选择时间范围 option[value='今天']\").text = \"yeahaha\";   <--- 这个没用\r\n  $(\"#keywords\").val(\"dddddd\");  <--- 这个有用\r\n```\r\n不知为何. 于是就找到之前的链接, 就以为是有某种限制了.",
            "created_at": "2017-09-03T16:53:04Z",
            "html_url": "https://github.com/program-in-chinese/HistoryInThreads_WebExtension/issues/3#issuecomment-326816597",
            "id": 326816597,
            "issue_url": "https://api.github.com/repos/program-in-chinese/HistoryInThreads_WebExtension/issues/3",
            "node_id": "MDEyOklzc3VlQ29tbWVudDMyNjgxNjU5Nw==",
            "updated_at": "2017-09-03T16:53:04Z",
            "url": "https://api.github.com/repos/program-in-chinese/HistoryInThreads_WebExtension/issues/comments/326816597",
            "user": {
                "avatar_url": "https://avatars1.githubusercontent.com/u/392497?v=4",
                "events_url": "https://api.github.com/users/nobodxbodon/events{/privacy}",
                "followers_url": "https://api.github.com/users/nobodxbodon/followers",
                "following_url": "https://api.github.com/users/nobodxbodon/following{/other_user}",
                "gists_url": "https://api.github.com/users/nobodxbodon/gists{/gist_id}",
                "gravatar_id": "",
                "html_url": "https://github.com/nobodxbodon",
                "id": 392497,
                "login": "nobodxbodon",
                "node_id": "MDQ6VXNlcjM5MjQ5Nw==",
                "organizations_url": "https://api.github.com/users/nobodxbodon/orgs",
                "received_events_url": "https://api.github.com/users/nobodxbodon/received_events",
                "repos_url": "https://api.github.com/users/nobodxbodon/repos",
                "site_admin": false,
                "starred_url": "https://api.github.com/users/nobodxbodon/starred{/owner}{/repo}",
                "subscriptions_url": "https://api.github.com/users/nobodxbodon/subscriptions",
                "type": "User",
                "url": "https://api.github.com/users/nobodxbodon"
            }
        },
        {
            "author_association": "NONE",
            "body": "innerText/innerHTML/textContent 等可用。.text 是别的属性。",
            "created_at": "2017-09-03T16:57:38Z",
            "html_url": "https://github.com/program-in-chinese/HistoryInThreads_WebExtension/issues/3#issuecomment-326816984",
            "id": 326816984,
            "issue_url": "https://api.github.com/repos/program-in-chinese/HistoryInThreads_WebExtension/issues/3",
            "node_id": "MDEyOklzc3VlQ29tbWVudDMyNjgxNjk4NA==",
            "updated_at": "2017-09-03T16:57:38Z",
            "url": "https://api.github.com/repos/program-in-chinese/HistoryInThreads_WebExtension/issues/comments/326816984",
            "user": {
                "avatar_url": "https://avatars0.githubusercontent.com/u/1769875?v=4",
                "events_url": "https://api.github.com/users/yfdyh000/events{/privacy}",
                "followers_url": "https://api.github.com/users/yfdyh000/followers",
                "following_url": "https://api.github.com/users/yfdyh000/following{/other_user}",
                "gists_url": "https://api.github.com/users/yfdyh000/gists{/gist_id}",
                "gravatar_id": "",
                "html_url": "https://github.com/yfdyh000",
                "id": 1769875,
                "login": "yfdyh000",
                "node_id": "MDQ6VXNlcjE3Njk4NzU=",
                "organizations_url": "https://api.github.com/users/yfdyh000/orgs",
                "received_events_url": "https://api.github.com/users/yfdyh000/received_events",
                "repos_url": "https://api.github.com/users/yfdyh000/repos",
                "site_admin": false,
                "starred_url": "https://api.github.com/users/yfdyh000/starred{/owner}{/repo}",
                "subscriptions_url": "https://api.github.com/users/yfdyh000/subscriptions",
                "type": "User",
                "url": "https://api.github.com/users/yfdyh000"
            }
        },
        {
            "author_association": "MEMBER",
            "body": "多谢, 不然就放弃了. 后来发现用`.text('...')`就行了, 太久没碰jquery了 :) \r\n已经提交2.0, 等待审核~. 用的老dynatree可能需要完整版, 搞不好通不过...",
            "created_at": "2017-09-03T23:11:11Z",
            "html_url": "https://github.com/program-in-chinese/HistoryInThreads_WebExtension/issues/3#issuecomment-326837729",
            "id": 326837729,
            "issue_url": "https://api.github.com/repos/program-in-chinese/HistoryInThreads_WebExtension/issues/3",
            "node_id": "MDEyOklzc3VlQ29tbWVudDMyNjgzNzcyOQ==",
            "updated_at": "2017-09-03T23:11:11Z",
            "url": "https://api.github.com/repos/program-in-chinese/HistoryInThreads_WebExtension/issues/comments/326837729",
            "user": {
                "avatar_url": "https://avatars1.githubusercontent.com/u/392497?v=4",
                "events_url": "https://api.github.com/users/nobodxbodon/events{/privacy}",
                "followers_url": "https://api.github.com/users/nobodxbodon/followers",
                "following_url": "https://api.github.com/users/nobodxbodon/following{/other_user}",
                "gists_url": "https://api.github.com/users/nobodxbodon/gists{/gist_id}",
                "gravatar_id": "",
                "html_url": "https://github.com/nobodxbodon",
                "id": 392497,
                "login": "nobodxbodon",
                "node_id": "MDQ6VXNlcjM5MjQ5Nw==",
                "organizations_url": "https://api.github.com/users/nobodxbodon/orgs",
                "received_events_url": "https://api.github.com/users/nobodxbodon/received_events",
                "repos_url": "https://api.github.com/users/nobodxbodon/repos",
                "site_admin": false,
                "starred_url": "https://api.github.com/users/nobodxbodon/starred{/owner}{/repo}",
                "subscriptions_url": "https://api.github.com/users/nobodxbodon/subscriptions",
                "type": "User",
                "url": "https://api.github.com/users/nobodxbodon"
            }
        }
    ],
    "comments": 5,
    "comments_url": "https://api.github.com/repos/program-in-chinese/HistoryInThreads_WebExtension/issues/3/comments",
    "created_at": "2017-09-01T04:26:32Z",
    "event_data": [
        {
            "actor": {
                "avatar_url": "https://avatars1.githubusercontent.com/u/392497?v=4",
                "events_url": "https://api.github.com/users/nobodxbodon/events{/privacy}",
                "followers_url": "https://api.github.com/users/nobodxbodon/followers",
                "following_url": "https://api.github.com/users/nobodxbodon/following{/other_user}",
                "gists_url": "https://api.github.com/users/nobodxbodon/gists{/gist_id}",
                "gravatar_id": "",
                "html_url": "https://github.com/nobodxbodon",
                "id": 392497,
                "login": "nobodxbodon",
                "node_id": "MDQ6VXNlcjM5MjQ5Nw==",
                "organizations_url": "https://api.github.com/users/nobodxbodon/orgs",
                "received_events_url": "https://api.github.com/users/nobodxbodon/received_events",
                "repos_url": "https://api.github.com/users/nobodxbodon/repos",
                "site_admin": false,
                "starred_url": "https://api.github.com/users/nobodxbodon/starred{/owner}{/repo}",
                "subscriptions_url": "https://api.github.com/users/nobodxbodon/subscriptions",
                "type": "User",
                "url": "https://api.github.com/users/nobodxbodon"
            },
            "commit_id": "0a4b85d295af52e14db486762fc705a5d9de68c8",
            "commit_url": "https://api.github.com/repos/program-in-chinese/HistoryInThreads_WebExtension/commits/0a4b85d295af52e14db486762fc705a5d9de68c8",
            "created_at": "2017-09-03T06:04:57Z",
            "event": "referenced",
            "id": 1232520969,
            "node_id": "MDE1OlJlZmVyZW5jZWRFdmVudDEyMzI1MjA5Njk=",
            "url": "https://api.github.com/repos/program-in-chinese/HistoryInThreads_WebExtension/issues/events/1232520969"
        },
        {
            "actor": {
                "avatar_url": "https://avatars1.githubusercontent.com/u/392497?v=4",
                "events_url": "https://api.github.com/users/nobodxbodon/events{/privacy}",
                "followers_url": "https://api.github.com/users/nobodxbodon/followers",
                "following_url": "https://api.github.com/users/nobodxbodon/following{/other_user}",
                "gists_url": "https://api.github.com/users/nobodxbodon/gists{/gist_id}",
                "gravatar_id": "",
                "html_url": "https://github.com/nobodxbodon",
                "id": 392497,
                "login": "nobodxbodon",
                "node_id": "MDQ6VXNlcjM5MjQ5Nw==",
                "organizations_url": "https://api.github.com/users/nobodxbodon/orgs",
                "received_events_url": "https://api.github.com/users/nobodxbodon/received_events",
                "repos_url": "https://api.github.com/users/nobodxbodon/repos",
                "site_admin": false,
                "starred_url": "https://api.github.com/users/nobodxbodon/starred{/owner}{/repo}",
                "subscriptions_url": "https://api.github.com/users/nobodxbodon/subscriptions",
                "type": "User",
                "url": "https://api.github.com/users/nobodxbodon"
            },
            "commit_id": "3e3ab904ba515bbc00e29a345d90f2c47a62b5b9",
            "commit_url": "https://api.github.com/repos/program-in-chinese/HistoryInThreads_WebExtension/commits/3e3ab904ba515bbc00e29a345d90f2c47a62b5b9",
            "created_at": "2017-09-03T21:25:06Z",
            "event": "referenced",
            "id": 1232731857,
            "node_id": "MDE1OlJlZmVyZW5jZWRFdmVudDEyMzI3MzE4NTc=",
            "url": "https://api.github.com/repos/program-in-chinese/HistoryInThreads_WebExtension/issues/events/1232731857"
        },
        {
            "actor": {
                "avatar_url": "https://avatars1.githubusercontent.com/u/392497?v=4",
                "events_url": "https://api.github.com/users/nobodxbodon/events{/privacy}",
                "followers_url": "https://api.github.com/users/nobodxbodon/followers",
                "following_url": "https://api.github.com/users/nobodxbodon/following{/other_user}",
                "gists_url": "https://api.github.com/users/nobodxbodon/gists{/gist_id}",
                "gravatar_id": "",
                "html_url": "https://github.com/nobodxbodon",
                "id": 392497,
                "login": "nobodxbodon",
                "node_id": "MDQ6VXNlcjM5MjQ5Nw==",
                "organizations_url": "https://api.github.com/users/nobodxbodon/orgs",
                "received_events_url": "https://api.github.com/users/nobodxbodon/received_events",
                "repos_url": "https://api.github.com/users/nobodxbodon/repos",
                "site_admin": false,
                "starred_url": "https://api.github.com/users/nobodxbodon/starred{/owner}{/repo}",
                "subscriptions_url": "https://api.github.com/users/nobodxbodon/subscriptions",
                "type": "User",
                "url": "https://api.github.com/users/nobodxbodon"
            },
            "commit_id": null,
            "commit_url": null,
            "created_at": "2017-09-03T23:11:11Z",
            "event": "closed",
            "id": 1232756371,
            "node_id": "MDExOkNsb3NlZEV2ZW50MTIzMjc1NjM3MQ==",
            "url": "https://api.github.com/repos/program-in-chinese/HistoryInThreads_WebExtension/issues/events/1232756371"
        }
    ],
    "events_url": "https://api.github.com/repos/program-in-chinese/HistoryInThreads_WebExtension/issues/3/events",
    "html_url": "https://github.com/program-in-chinese/HistoryInThreads_WebExtension/issues/3",
    "id": 254532851,
    "labels": [],
    "labels_url": "https://api.github.com/repos/program-in-chinese/HistoryInThreads_WebExtension/issues/3/labels{/name}",
    "locked": false,
    "milestone": null,
    "node_id": "MDU6SXNzdWUyNTQ1MzI4NTE=",
    "number": 3,
    "repository_url": "https://api.github.com/repos/program-in-chinese/HistoryInThreads_WebExtension",
    "state": "closed",
    "title": "界面字符串多语言支持",
    "updated_at": "2017-09-03T23:11:11Z",
    "url": "https://api.github.com/repos/program-in-chinese/HistoryInThreads_WebExtension/issues/3",
    "user": {
        "avatar_url": "https://avatars1.githubusercontent.com/u/392497?v=4",
        "events_url": "https://api.github.com/users/nobodxbodon/events{/privacy}",
        "followers_url": "https://api.github.com/users/nobodxbodon/followers",
        "following_url": "https://api.github.com/users/nobodxbodon/following{/other_user}",
        "gists_url": "https://api.github.com/users/nobodxbodon/gists{/gist_id}",
        "gravatar_id": "",
        "html_url": "https://github.com/nobodxbodon",
        "id": 392497,
        "login": "nobodxbodon",
        "node_id": "MDQ6VXNlcjM5MjQ5Nw==",
        "organizations_url": "https://api.github.com/users/nobodxbodon/orgs",
        "received_events_url": "https://api.github.com/users/nobodxbodon/received_events",
        "repos_url": "https://api.github.com/users/nobodxbodon/repos",
        "site_admin": false,
        "starred_url": "https://api.github.com/users/nobodxbodon/starred{/owner}{/repo}",
        "subscriptions_url": "https://api.github.com/users/nobodxbodon/subscriptions",
        "type": "User",
        "url": "https://api.github.com/users/nobodxbodon"
    }
}