{
    "assignee": null,
    "assignees": [],
    "author_association": "MEMBER",
    "body": "https://gitee.com/didispace/SpringBoot-Learning/blob/master/Chapter3-1-1/src/main/java/com/didispace/domain/User.java\r\n火狐:\r\n![screen shot 2018-11-05 at 11 30 22 pm](https://user-images.githubusercontent.com/392497/48049227-d2806d80-e152-11e8-91cf-3b54db4e79ad.png)\r\nChrome:\r\n![screen shot 2018-11-05 at 11 30 56 pm](https://user-images.githubusercontent.com/392497/48049253-e62bd400-e152-11e8-87e8-bb11f8db62e0.png)\r\n\r\n",
    "closed_at": "2018-11-06T08:37:52Z",
    "comment_data": [],
    "comments": 0,
    "comments_url": "https://api.github.com/repos/program-in-chinese/webextension_github_code_translator/issues/23/comments",
    "created_at": "2018-11-06T07:31:27Z",
    "event_data": [
        {
            "actor": {
                "avatar_url": "https://avatars1.githubusercontent.com/u/392497?v=4",
                "events_url": "https://api.github.com/users/nobodxbodon/events{/privacy}",
                "followers_url": "https://api.github.com/users/nobodxbodon/followers",
                "following_url": "https://api.github.com/users/nobodxbodon/following{/other_user}",
                "gists_url": "https://api.github.com/users/nobodxbodon/gists{/gist_id}",
                "gravatar_id": "",
                "html_url": "https://github.com/nobodxbodon",
                "id": 392497,
                "login": "nobodxbodon",
                "node_id": "MDQ6VXNlcjM5MjQ5Nw==",
                "organizations_url": "https://api.github.com/users/nobodxbodon/orgs",
                "received_events_url": "https://api.github.com/users/nobodxbodon/received_events",
                "repos_url": "https://api.github.com/users/nobodxbodon/repos",
                "site_admin": false,
                "starred_url": "https://api.github.com/users/nobodxbodon/starred{/owner}{/repo}",
                "subscriptions_url": "https://api.github.com/users/nobodxbodon/subscriptions",
                "type": "User",
                "url": "https://api.github.com/users/nobodxbodon"
            },
            "commit_id": "d0c2a598b1b64a9ed2484501ae8f310af13fb951",
            "commit_url": "https://api.github.com/repos/program-in-chinese/webextension_github_code_translator/commits/d0c2a598b1b64a9ed2484501ae8f310af13fb951",
            "created_at": "2018-11-06T08:24:44Z",
            "event": "referenced",
            "id": 1948275380,
            "node_id": "MDE1OlJlZmVyZW5jZWRFdmVudDE5NDgyNzUzODA=",
            "url": "https://api.github.com/repos/program-in-chinese/webextension_github_code_translator/issues/events/1948275380"
        },
        {
            "actor": {
                "avatar_url": "https://avatars1.githubusercontent.com/u/392497?v=4",
                "events_url": "https://api.github.com/users/nobodxbodon/events{/privacy}",
                "followers_url": "https://api.github.com/users/nobodxbodon/followers",
                "following_url": "https://api.github.com/users/nobodxbodon/following{/other_user}",
                "gists_url": "https://api.github.com/users/nobodxbodon/gists{/gist_id}",
                "gravatar_id": "",
                "html_url": "https://github.com/nobodxbodon",
                "id": 392497,
                "login": "nobodxbodon",
                "node_id": "MDQ6VXNlcjM5MjQ5Nw==",
                "organizations_url": "https://api.github.com/users/nobodxbodon/orgs",
                "received_events_url": "https://api.github.com/users/nobodxbodon/received_events",
                "repos_url": "https://api.github.com/users/nobodxbodon/repos",
                "site_admin": false,
                "starred_url": "https://api.github.com/users/nobodxbodon/starred{/owner}{/repo}",
                "subscriptions_url": "https://api.github.com/users/nobodxbodon/subscriptions",
                "type": "User",
                "url": "https://api.github.com/users/nobodxbodon"
            },
            "commit_id": "1689f64ac0f0a77ce96667e1f5b843226a0d41f8",
            "commit_url": "https://api.github.com/repos/program-in-chinese/webextension_github_code_translator/commits/1689f64ac0f0a77ce96667e1f5b843226a0d41f8",
            "created_at": "2018-11-06T08:28:39Z",
            "event": "referenced",
            "id": 1948282187,
            "node_id": "MDE1OlJlZmVyZW5jZWRFdmVudDE5NDgyODIxODc=",
            "url": "https://api.github.com/repos/program-in-chinese/webextension_github_code_translator/issues/events/1948282187"
        },
        {
            "actor": {
                "avatar_url": "https://avatars1.githubusercontent.com/u/392497?v=4",
                "events_url": "https://api.github.com/users/nobodxbodon/events{/privacy}",
                "followers_url": "https://api.github.com/users/nobodxbodon/followers",
                "following_url": "https://api.github.com/users/nobodxbodon/following{/other_user}",
                "gists_url": "https://api.github.com/users/nobodxbodon/gists{/gist_id}",
                "gravatar_id": "",
                "html_url": "https://github.com/nobodxbodon",
                "id": 392497,
                "login": "nobodxbodon",
                "node_id": "MDQ6VXNlcjM5MjQ5Nw==",
                "organizations_url": "https://api.github.com/users/nobodxbodon/orgs",
                "received_events_url": "https://api.github.com/users/nobodxbodon/received_events",
                "repos_url": "https://api.github.com/users/nobodxbodon/repos",
                "site_admin": false,
                "starred_url": "https://api.github.com/users/nobodxbodon/starred{/owner}{/repo}",
                "subscriptions_url": "https://api.github.com/users/nobodxbodon/subscriptions",
                "type": "User",
                "url": "https://api.github.com/users/nobodxbodon"
            },
            "commit_id": null,
            "commit_url": null,
            "created_at": "2018-11-06T08:37:52Z",
            "event": "closed",
            "id": 1948299599,
            "node_id": "MDExOkNsb3NlZEV2ZW50MTk0ODI5OTU5OQ==",
            "url": "https://api.github.com/repos/program-in-chinese/webextension_github_code_translator/issues/events/1948299599"
        }
    ],
    "events_url": "https://api.github.com/repos/program-in-chinese/webextension_github_code_translator/issues/23/events",
    "html_url": "https://github.com/program-in-chinese/webextension_github_code_translator/issues/23",
    "id": 377723340,
    "labels": [],
    "labels_url": "https://api.github.com/repos/program-in-chinese/webextension_github_code_translator/issues/23/labels{/name}",
    "locked": false,
    "milestone": null,
    "node_id": "MDU6SXNzdWUzNzc3MjMzNDA=",
    "number": 23,
    "repository_url": "https://api.github.com/repos/program-in-chinese/webextension_github_code_translator",
    "state": "closed",
    "title": "当码云网页处于登录状态时, 弹窗内容错误",
    "updated_at": "2018-11-06T08:37:52Z",
    "url": "https://api.github.com/repos/program-in-chinese/webextension_github_code_translator/issues/23",
    "user": {
        "avatar_url": "https://avatars1.githubusercontent.com/u/392497?v=4",
        "events_url": "https://api.github.com/users/nobodxbodon/events{/privacy}",
        "followers_url": "https://api.github.com/users/nobodxbodon/followers",
        "following_url": "https://api.github.com/users/nobodxbodon/following{/other_user}",
        "gists_url": "https://api.github.com/users/nobodxbodon/gists{/gist_id}",
        "gravatar_id": "",
        "html_url": "https://github.com/nobodxbodon",
        "id": 392497,
        "login": "nobodxbodon",
        "node_id": "MDQ6VXNlcjM5MjQ5Nw==",
        "organizations_url": "https://api.github.com/users/nobodxbodon/orgs",
        "received_events_url": "https://api.github.com/users/nobodxbodon/received_events",
        "repos_url": "https://api.github.com/users/nobodxbodon/repos",
        "site_admin": false,
        "starred_url": "https://api.github.com/users/nobodxbodon/starred{/owner}{/repo}",
        "subscriptions_url": "https://api.github.com/users/nobodxbodon/subscriptions",
        "type": "User",
        "url": "https://api.github.com/users/nobodxbodon"
    }
}